[
  {
    "headline": "Is AstraZeneca PLC (AZN) the Best Foreign Dividend Stock to Buy According to Analysts?",
    "url": "https://finance.yahoo.com/news/astrazeneca-plc-azn-best-foreign-113052343.html?.tsrc=rss",
    "publication_date": "2025-02-14T11:30:52.000Z",
    "full_article_text": "No content found"
  },
  {
    "headline": "3 UK Stocks That May Be Undervalued Based On Current Estimates",
    "url": "https://finance.yahoo.com/news/3-uk-stocks-may-undervalued-110224719.html?.tsrc=rss",
    "publication_date": "2025-02-12T11:02:24.000Z",
    "full_article_text": "No content found"
  },
  {
    "headline": "AstraZeneca PLC (AZN): Among the Best International Dividend Stocks to Buy Now",
    "url": "https://finance.yahoo.com/news/astrazeneca-plc-azn-among-best-054339778.html?.tsrc=rss",
    "publication_date": "2025-02-12T05:43:39.000Z",
    "full_article_text": "No content found"
  }
]