[
  {
    "headline": "Biotech Stock Roundup: GILD Up on Q4 Results, BIIB, BMY Down on 2025 Guidance",
    "url": "https://finance.yahoo.com/news/biotech-stock-roundup-gild-q4-180200974.html?.tsrc=rss",
    "publication_date": "2025-02-13T18:02:00.000Z",
    "full_article_text": "No content found"
  },
  {
    "headline": "Gilead Sciences (GILD) is a Top-Ranked Momentum Stock: Should You Buy?",
    "url": "https://finance.yahoo.com/news/gilead-sciences-gild-top-ranked-145014065.html?.tsrc=rss",
    "publication_date": "2025-02-13T14:50:14.000Z",
    "full_article_text": "No content found"
  },
  {
    "headline": "3 US Stocks Estimated Up To 48.1% Undervalued Based On Intrinsic Value Estimates",
    "url": "https://finance.yahoo.com/news/3-us-stocks-estimated-48-100217470.html?.tsrc=rss",
    "publication_date": "2025-02-13T10:02:17.000Z",
    "full_article_text": "No content found"
  }
]