[
  {
    "headline": "Is Arcos Dorados (ARCO) a Mispriced Stock?",
    "url": "https://finance.yahoo.com/news/arcos-dorados-arco-mispriced-stock-133142626.html?.tsrc=rss",
    "publication_date": "2025-02-13T13:31:42.000Z",
    "full_article_text": "No content found"
  },
  {
    "headline": "Meet the Adults Who Swear By the Kids\u2019 Menu. \u2018Give Me Chicken Tenders and I\u2019m Happy.\u2019",
    "url": "https://finance.yahoo.com/m/b19cdf9a-7137-3474-80ca-58cdc133bf7a/meet-the-adults-who-swear-by.html?.tsrc=rss",
    "publication_date": "2025-02-13T10:30:00.000Z",
    "full_article_text": "No content found"
  },
  {
    "headline": "Best Stock to Buy Right Now: Domino's Pizza vs. McDonald's",
    "url": "https://www.fool.com/investing/2025/02/13/best-stock-to-buy-right-now-dominos-pizza-vs-mcdon/?source=eptyholnk0000202&utm_source=yahoo-host-full&utm_medium=feed&utm_campaign=article&referring_guid=ba15e2e8-4e8d-47fc-80b6-fbed1c73c5f8&.tsrc=rss",
    "publication_date": "No publication date found",
    "full_article_text": "No content found"
  }
]